ansible_argspec_gen/__init__.py
ansible_argspec_gen/cli.py
ansible_argspec_gen/utils.py
ansible_argspec_gen-0.1.1.dist-info/LICENSE
ansible_argspec_gen-0.1.1.dist-info/METADATA
ansible_argspec_gen-0.1.1.dist-info/WHEEL
ansible_argspec_gen-0.1.1.dist-info/entry_points.txt
ansible_argspec_gen-0.1.1.dist-info/top_level.txt
ansible_argspec_gen-0.1.1.dist-info/zip-safe
ansible_argspec_gen-0.1.1.dist-info/RECORD
