Metadata-Version: 2.1
Name: ansible-argspec-gen
Version: 0.1.1
Summary: Generate Ansible argument specification from API docs
Home-page: UNKNOWN
Author: XLAB Steampunk
Author-email: steampunk@xlab.si
License: UNKNOWN
Keywords: ansible,development
Platform: UNKNOWN
Classifier: Development Status :: 2 - Pre-Alpha
Classifier: Environment :: Console
Classifier: Intended Audience :: Developers
Classifier: License :: OSI Approved :: GNU Lesser General Public License v3 or later (LGPLv3+)
Classifier: Programming Language :: Python
Classifier: Programming Language :: Python :: 3
Classifier: Programming Language :: Python :: 3.6
Classifier: Programming Language :: Python :: 3.7
Classifier: Programming Language :: Python :: 3.8
Requires-Dist: black
Provides-Extra: ansible
Requires-Dist: ansible ; extra == 'ansible'
Provides-Extra: base
Requires-Dist: ansible-base ; extra == 'base'
